{"shader":"body3fluxzy1.shader.json","srcshader":"Gd3d/Body3Fluxzy1","queue":0,"mapUniform":{"_MatCapColor":{"type":3,"value":"(1,1,1,1)"},"_MatCap2Color":{"type":3,"value":"(1,1,1,1)"},"_MatCap3Color":{"type":3,"value":"(1,1,1,1)"},"_Strength":{"type":1,"value":1.24000000953674},"_Strength2":{"type":1,"value":1.58000004291534},"_Strength3":{"type":1,"value":1.63999998569489},"_MainTex":{"type":0,"value":"NPC.imgdesc.json"},"_BumpMap":{"type":0,"value":"NPC_N.imgdesc.json"},"_MaskTex":{"type":0,"value":"NPC_rm.imgdesc.json"},"_MatCap":{"type":0,"value":"77.imgdesc.json"},"_MatCap2":{},"_MatCap3":{},"_FluxayTex":{},"_FluxayColor":{"type":3,"value":"(0.5,0.5,0.5,1)"},"_FluxayTex2":{},"_FluxayColor2":{"type":3,"value":"(0.5,0.5,0.5,1)"},"_MatCapAccurate":{"type":1,"value":0}},"InstanceID":"9090"}