{"shader":"bodyfluxzy2.shader.json","srcshader":"Gd3d/BodyFluxzy2","queue":0,"mapUniform":{"_MatCapColor":{"type":3,"value":"(1,1,1,1)"},"_MatCap2Color":{"type":3,"value":"(1,1,1,1)"},"_Strength":{"type":1,"value":1.5},"_Strength2":{"type":1,"value":1.04999995231628},"_MainTex":{"type":0,"value":"tangbing_Base_Color.imgdesc.json"},"_BumpMap":{},"_MaskTex":{"type":0,"value":"tangbing_texture.imgdesc.json"},"_MatCap":{"type":0,"value":"6.imgdesc.json"},"_MatCap2":{},"_FluxayTex":{},"_FluxayColor":{"type":3,"value":"(0.5,0.5,0.5,1)"},"_FluxayTex2":{},"_FluxayColor2":{"type":3,"value":"(0.5,0.5,0.5,1)"},"_MatCapAccurate":{"type":1,"value":0}},"InstanceID":"-68906"}